cdp_langchain/__init__.py
cdp_langchain/__version__.py
cdp_langchain/agent_toolkits/__init__.py
cdp_langchain/agent_toolkits/cdp_toolkit.py
cdp_langchain/constants.py
cdp_langchain/tools/__init__.py
cdp_langchain/tools/cdp_tool.py
cdp_langchain/utils/__init__.py
cdp_langchain/utils/cdp_agentkit_wrapper.py
cdp_langchain-0.0.12.dist-info/METADATA
cdp_langchain-0.0.12.dist-info/WHEEL
cdp_langchain-0.0.12.dist-info/RECORD
