Metadata-Version: 2.3
Name: cdp-langchain
Version: 0.0.12
Summary: CDP Agentkit Langchain Extension
License: Apache-2.0
Keywords: coinbase,sdk,crypto,cdp,agentkit,ai,agent,langchain,toolkit
Author: John Peterson
Author-email: john.peterson@coinbase.com
Requires-Python: >=3.10,<4.0
Classifier: License :: OSI Approved :: Apache Software License
Classifier: Programming Language :: Python :: 3
Classifier: Programming Language :: Python :: 3.10
Classifier: Programming Language :: Python :: 3.11
Classifier: Programming Language :: Python :: 3.12
Classifier: Programming Language :: Python :: 3.13
Requires-Dist: cdp-agentkit-core (>=0.0.10,<0.0.11)
Requires-Dist: cdp-sdk (>=0.14.1,<0.15.0)
Requires-Dist: langchain (>=0.3.4,<0.4.0)
Requires-Dist: langchain-openai (>=0.2.4,<0.3.0)
Requires-Dist: langgraph (>=0.2.39,<0.3.0)
Requires-Dist: pydantic (>=2.0,<3.0)
